example/fifo_latency/fifo.sv
module fifo #(
    parameter DEPTH = 2,
    DATA_WIDTH = 8
) (
    input clk,
    input rst_n,
    input w_en,
    input r_en,
    input [DATA_WIDTH-1:0] data_in,
    output reg [DATA_WIDTH-1:0] data_out,
    output full,
    output empty
);

    reg [$clog2(DEPTH)-1:0] w_ptr, r_ptr;
    reg [DATA_WIDTH-1:0] fifo[DEPTH];

    // Set Default values on reset.
    always @(posedge clk) begin
        if (!rst_n) begin
            w_ptr <= 0;
            r_ptr <= 0;
            data_out <= 0;
        end
    end

    // To write data to FIFO
    always @(posedge clk) begin
        if (w_en & !full) begin
            fifo[w_ptr] <= data_in;
            w_ptr <= w_ptr + 1;
        end
    end

    // To read data from FIFO
    always @(posedge clk) begin
        if (r_en & !empty) begin
            data_out <= fifo[r_ptr];
            r_ptr <= r_ptr + 1;
        end
    end

    assign full  = ((w_ptr + 1'b1) == r_ptr);
    assign empty = (w_ptr == r_ptr);
endmodule

example/fifo_latency/fifo_tb.sv
module fifo_tb;
    parameter DATA_WIDTH = 8;

    reg clk, rst_n;
    reg w_en, r_en;
    reg  [DATA_WIDTH-1:0] data_in;
    wire [DATA_WIDTH-1:0] data_out;
    wire full, empty;

    fifo s_fifo (
        clk,
        rst_n,
        w_en,
        r_en,
        data_in,
        data_out,
        full,
        empty
    );

    always #5 clk = ~clk;

    initial begin
        clk = 1'b0;
        rst_n = 1'b0;
        w_en = 1'b0;
        data_in = 0;

        repeat (10) @(posedge clk);
        rst_n = 1'b1;

        repeat (2) begin
            for (int i = 0; i < 30; i++) begin
                @(posedge clk);
                data_in = $urandom;
                if (w_en && full) begin
                    w_en <= 1'b1;
                end else begin
                    w_en <= (i % 2 == 0) ? 1'b1 : 1'b0;
                end

                if (w_en & !full) begin
                    $display("[%0t] wdata = %0d", $time, data_in);
                end
            end
            #50;
        end
    end

    initial begin
        clk   = 1'b0;
        rst_n = 1'b0;
        r_en  = 1'b0;

        repeat (20) @(posedge clk);
        rst_n = 1'b1;

        repeat (2) begin
            for (int i = 0; i < 30; i++) begin
                @(posedge clk);
                #1;
                r_en = (i % 4 == 0) ? 1'b1 : 1'b0;
                if (r_en & !empty) begin
                    $display("[%0t] rdata = %0d", $time, data_out);
                end
            end
            #50;
        end

        $finish;
    end

    initial begin
        $dumpfile("fifo_tb.vcd");
        $dumpvars;
    end
endmodule

example/fifo_latency/fifo_tb.vcd
$date
	Sun Jan 25 20:13:54 2026
$end
$version
	Icarus Verilog
$end
$timescale
	1s
$end
$scope module fifo_tb $end
$var wire 1 ! full $end
$var wire 1 " empty $end
$var wire 8 # data_out [7:0] $end
$var parameter 32 $ DATA_WIDTH $end
$var reg 1 % clk $end
$var reg 8 & data_in [7:0] $end
$var reg 1 ' r_en $end
$var reg 1 ( rst_n $end
$var reg 1 ) w_en $end
$scope module s_fifo $end
$var wire 1 % clk $end
$var wire 8 * data_in [7:0] $end
$var wire 1 " empty $end
$var wire 1 ! full $end
$var wire 1 ' r_en $end
$var wire 1 ( rst_n $end
$var wire 1 ) w_en $end
$var parameter 32 + DATA_WIDTH $end
$var parameter 32 , DEPTH $end
$var reg 8 - data_out [7:0] $end
$var reg 1 . r_ptr $end
$var reg 1 / w_ptr $end
$upscope $end
$scope begin $ivl_for_loop0 $end
$var integer 32 0 i [31:0] $end
$upscope $end
$scope begin $ivl_for_loop1 $end
$var integer 32 1 i [31:0] $end
$upscope $end
$upscope $end
$enddefinitions $end
$comment Show the parameter values. $end
$dumpall
b10 ,
b1000 +
b1000 $
$end
#0
$dumpvars
b0 1
b0 0
x/
x.
bx -
b0 *
0)
0(
0'
b0 &
0%
bx #
x"
x!
$end
#5
0!
1"
b0 #
b0 -
0.
0/
1%
#10
0%
#15
1%
#20
0%
#25
1%
#30
0%
#35
1%
#40
0%
#45
1%
#50
0%
#55
1%
#60
0%
#65
1%
#70
0%
#75
1%
#80
0%
#85
1%
#90
0%
#95
1(
1%
#100
0%
#105
1)
b1 0
b100100 &
b100100 *
1%
#110
0%
#115
1!
0"
0)
1/
b10 0
b10000001 &
b10000001 *
1%
#120
0%
#125
1)
b11 0
b1001 &
b1001 *
1%
#130
0%
#135
b100 0
b1100011 &
b1100011 *
1%
#140
0%
#145
b101 0
b1101 &
b1101 *
1%
#150
0%
#155
b110 0
b10001101 &
b10001101 *
1%
#160
0%
#165
b111 0
b1100101 &
b1100101 *
1%
#170
0%
#175
b1000 0
b10010 &
b10010 *
1%
#180
0%
#185
b1001 0
b1 &
b1 *
1%
#190
0%
#195
b1010 0
b1101 &
b1101 *
1%
#200
0%
#205
b1011 0
b1110110 &
b1110110 *
1%
#206
b1 1
1'
#210
0%
#215
1"
0!
1.
b100100 #
b100100 -
b1100 0
b111101 &
b111101 *
1%
#216
b10 1
0'
#220
0%
#225
1!
0"
0/
b1101 0
b11101101 &
b11101101 *
1%
#226
b11 1
#230
0%
#235
b1110 0
b10001100 &
b10001100 *
1%
#236
b100 1
#240
0%
#245
b1111 0
b11111001 &
b11111001 *
1%
#246
b101 1
1'
#250
0%
#255
1"
0!
0.
b11101101 #
b11101101 -
b10000 0
b11000110 &
b11000110 *
1%
#256
b110 1
0'
#260
0%
#265
1!
0"
1/
b10001 0
b11000101 &
b11000101 *
1%
#266
b111 1
#270
0%
#275
b10010 0
b10101010 &
b10101010 *
1%
#276
b1000 1
#280
0%
#285
b10011 0
b11100101 &
b11100101 *
1%
#286
b1001 1
1'
#290
0%
#295
1"
0!
1.
b11000101 #
b11000101 -
b10100 0
b1110111 &
b1110111 *
1%
#296
b1010 1
0'
#300
0%
#305
1!
0"
0/
b10101 0
b10010 &
b10010 *
1%
#306
b1011 1
#310
0%
#315
b10110 0
b10001111 &
b10001111 *
1%
#316
b1100 1
#320
0%
#325
b10111 0
b11110010 &
b11110010 *
1%
#326
b1101 1
1'
#330
0%
#335
1"
0!
0.
b10010 #
b10010 -
b11000 0
b11001110 &
b11001110 *
1%
#336
b1110 1
0'
#340
0%
#345
1!
0"
1/
b11001 0
b11101000 &
b11101000 *
1%
#346
b1111 1
#350
0%
#355
b11010 0
b11000101 &
b11000101 *
1%
#356
b10000 1
#360
0%
#365
b11011 0
b1011100 &
b1011100 *
1%
#366
b10001 1
1'
#370
0%
#375
1"
0!
1.
b11101000 #
b11101000 -
b11100 0
b10111101 &
b10111101 *
1%
#376
b10010 1
0'
#380
0%
#385
1!
0"
0/
b11101 0
b101101 &
b101101 *
1%
#386
b10011 1
#390
0%
#395
b11110 0
b1100101 &
b1100101 *
1%
#396
b10100 1
#400
0%
#405
1%
#406
b10101 1
1'
#410
0%
#415
1"
0!
0.
b101101 #
b101101 -
1%
#416
b10110 1
0'
#420
0%
#425
1!
0"
1/
1%
#426
b10111 1
#430
0%
#435
1%
#436
b11000 1
#440
0%
#445
b1100011 &
b1100011 *
1%
b1 0
#446
b11001 1
1'
#450
0%
#455
1"
0!
1.
b1100101 #
b1100101 -
b10 0
b1010 &
b1010 *
1%
#456
b11010 1
0'
#460
0%
#465
1!
0"
0/
b11 0
b10000000 &
b10000000 *
1%
#466
b11011 1
#470
0%
#475
b100 0
b100000 &
b100000 *
1%
#476
b11100 1
#480
0%
#485
b101 0
b10101010 &
b10101010 *
1%
#486
b11101 1
1'
#490
0%
#495
1"
0!
0.
b10000000 #
b10000000 -
b110 0
b10011101 &
b10011101 *
1%
#496
b11110 1
0'
#500
0%
#505
1!
0"
1/
b111 0
b10010110 &
b10010110 *
1%
#510
0%
#515
b1000 0
b10011 &
b10011 *
1%
#520
0%
#525
b1001 0
b1101 &
b1101 *
1%
#530
0%
#535
b1010 0
b1010011 &
b1010011 *
1%
#540
0%
#545
b1011 0
b1101011 &
b1101011 *
1%
#546
b0 1
#550
0%
#555
b1100 0
b11010101 &
b11010101 *
1%
#556
b1 1
1'
#560
0%
#565
1"
0!
1.
b10010110 #
b10010110 -
b1101 0
b10 &
b10 *
1%
#566
b10 1
0'
#570
0%
#575
1!
0"
0)
0/
b1110 0
b10101110 &
b10101110 *
1%
#576
b11 1
#580
0%
#585
1)
b1111 0
b11101 &
b11101 *
1%
#586
b100 1
#590
0%
#595
b10000 0
b11001111 &
b11001111 *
1%
#596
b101 1
1'
#600
0%
#605
1"
0!
0.
b10 #
b10 -
b10001 0
b100011 &
b100011 *
1%
#606
b110 1
0'
#610
0%
#615
1!
0"
0)
1/
b10010 0
b1010 &
b1010 *
1%
#616
b111 1
#620
0%
#625
1)
b10011 0
b11001010 &
b11001010 *
1%
#626
b1000 1
#630
0%
#635
b10100 0
b111100 &
b111100 *
1%
#636
b1001 1
1'
#640
0%
#645
1"
0!
1.
b100011 #
b100011 -
b10101 0
b11110010 &
b11110010 *
1%
#646
b1010 1
0'
#650
0%
#655
1!
0"
0)
0/
b10110 0
b10001010 &
b10001010 *
1%
#656
b1011 1
#660
0%
#665
1)
b10111 0
b1000001 &
b1000001 *
1%
#666
b1100 1
#670
0%
#675
b11000 0
b11011000 &
b11011000 *
1%
#676
b1101 1
1'
#680
0%
#685
1"
0!
0.
b11110010 #
b11110010 -
b11001 0
b1111000 &
b1111000 *
1%
#686
b1110 1
0'
#690
0%
#695
1!
0"
0)
1/
b11010 0
b10001001 &
b10001001 *
1%
#696
b1111 1
#700
0%
#705
1)
b11011 0
b11101011 &
b11101011 *
1%
#706
b10000 1
#710
0%
#715
b11100 0
b10110110 &
b10110110 *
1%
#716
b10001 1
1'
#720
0%
#725
1"
0!
1.
b1111000 #
b1111000 -
b11101 0
b11000110 &
b11000110 *
1%
#726
b10010 1
0'
#730
0%
#735
1!
0"
0)
0/
b11110 0
b10101110 &
b10101110 *
1%
#736
b10011 1
#740
0%
#745
1%
#746
b10100 1
#750
0%
#755
1%
#756
b10101 1
1'
#760
0%
#765
1"
0!
0.
b11000110 #
b11000110 -
1%
#766
b10110 1
0'
#770
0%
#775
1%
#776
b10111 1
#780
0%
#785
1%
#786
b11000 1
#790
0%
#795
1%
#796
b11001 1
1'
#800
0%
#805
1%
#806
b11010 1
0'
#810
0%
#815
1%
#816
b11011 1
#820
0%
#825
1%
#826
b11100 1
#830
0%
#835
1%
#836
b11101 1
1'
#840
0%
#845
1%
#846
b11110 1
0'
