example/fifo_latency/fifo.sv
module fifo #(
    parameter DEPTH = 2,
    DATA_WIDTH = 8
) (
    input clk,
    input rst_n,
    input w_en,
    input r_en,
    input [DATA_WIDTH-1:0] data_in,
    output reg [DATA_WIDTH-1:0] data_out,
    output full,
    output empty
);

    reg [$clog2(DEPTH)-1:0] w_ptr, r_ptr;
    reg [DATA_WIDTH-1:0] fifo[DEPTH];

    // Set Default values on reset.
    always @(posedge clk) begin
        if (!rst_n) begin
            w_ptr <= 0;
            r_ptr <= 0;
            data_out <= 0;
        end
    end

    // To write data to FIFO
    always @(posedge clk) begin
        if (w_en & !full) begin
            fifo[w_ptr] <= data_in;
            w_ptr <= w_ptr + 1;
        end
    end

    // To read data from FIFO
    always @(posedge clk) begin
        if (r_en & !empty) begin
            data_out <= fifo[r_ptr];
            r_ptr <= r_ptr + 1;
        end
    end

    assign full  = ((w_ptr + 1'b1) == r_ptr);
    assign empty = (w_ptr == r_ptr);
endmodule

example/scoreboard/fifo_tb.sv
module fifo_tb;
    parameter DATA_WIDTH = 8;

    reg clk, rst_n;
    reg w_en, r_en;
    reg  [DATA_WIDTH-1:0] data_in;
    wire [DATA_WIDTH-1:0] data_out;
    wire full, empty;

    fifo s_fifo (
        clk,
        rst_n,
        w_en,
        r_en,
        data_in,
        data_out,
        full,
        empty
    );

    always #5 clk = ~clk;

    initial begin
        clk = 1'b0;
        rst_n = 1'b0;
        w_en = 1'b0;
        data_in = 0;

        repeat (10) @(posedge clk);
        rst_n = 1'b1;

        // Ensure write starts after reset and gives some time
        #20;

        repeat (5) begin
            for (int i = 0; i < 30; i++) begin
                @(posedge clk);
                #1;
                data_in = $urandom;
                // Randomized write enable
                w_en = (i % 2 == 0) ? 1'b1 : 1'b0;

                if (w_en & !full) begin
                    $display("[%0t] wdata = %0d", $time, data_in);
                end
            end
            #50;
        end
    end

    initial begin
        clk   = 1'b0;
        rst_n = 1'b0;
        r_en  = 1'b0;

        repeat (20) @(posedge clk);
        rst_n = 1'b1;

        // Wait for some data to be written
        // Wait until at least one write has happened
        @(posedge clk);
        wait (s_fifo.w_ptr != 0);
        #1; // Delay to avoid sampling issues if r_en goes high same cycle? No, just wait a bit.

        repeat (5) begin
            for (int i = 0; i < 30; i++) begin
                @(posedge clk);
                #1;
                // Randomized read enable
                r_en = (i % 3 == 0) ? 1'b1 : 1'b0;
                if (r_en & !empty) begin
                    $display("[%0t] rdata = %0d", $time, data_out);
                end
            end
            #50;
        end

        $finish;
    end

    initial begin
        $dumpfile("fifo_tb.vcd");
        $dumpvars;
    end
endmodule

example/fifo_average_occupancy_level/fifo_tb.vcd
$date
	Sun Dec  1 23:56:39 2024
$end
$version
	Icarus Verilog
$end
$timescale
	1s
$end
$scope module fifo_tb $end
$var wire 1 ! full $end
$var wire 1 " empty $end
$var wire 8 # data_out [7:0] $end
$var parameter 32 $ DATA_WIDTH $end
$var reg 1 % clk $end
$var reg 8 & data_in [7:0] $end
$var reg 1 ' r_en $end
$var reg 1 ( rst_n $end
$var reg 1 ) w_en $end
$scope module s_fifo $end
$var wire 1 % clk $end
$var wire 8 * data_in [7:0] $end
$var wire 1 ' r_en $end
$var wire 1 ( rst_n $end
$var wire 1 ) w_en $end
$var wire 1 ! full $end
$var wire 1 " empty $end
$var parameter 32 + DATA_WIDTH $end
$var parameter 32 , DEPTH $end
$var reg 8 - data_out [7:0] $end
$var reg 3 . r_ptr [2:0] $end
$var reg 3 / w_ptr [2:0] $end
$upscope $end
$scope begin $ivl_for_loop0 $end
$var integer 32 0 i [31:0] $end
$upscope $end
$scope begin $ivl_for_loop1 $end
$var integer 32 1 i [31:0] $end
$upscope $end
$upscope $end
$enddefinitions $end
$comment Show the parameter values. $end
$dumpall
b1000 ,
b1000 +
b1000 $
$end
#0
$dumpvars
b0 1
b0 0
bx /
bx .
bx -
b0 *
0)
0(
0'
b0 &
0%
bx #
x"
x!
$end
#5
b0 #
b0 -
0!
1"
b0 .
b0 /
1%
#10
0%
#15
1%
#20
0%
#25
1%
#30
0%
#35
1%
#40
0%
#45
1%
#50
0%
#55
1%
#60
0%
#65
1%
#70
0%
#75
1%
#80
0%
#85
1%
#90
0%
#95
1(
1%
#100
0%
#105
1%
#106
b1 0
1)
b100100 &
b100100 *
#110
0%
#115
0"
b1 /
1%
#116
b10 0
0)
b10000001 &
b10000001 *
#120
0%
#125
1%
#126
b11 0
1)
b1001 &
b1001 *
#130
0%
#135
b10 /
1%
#136
b100 0
0)
b1100011 &
b1100011 *
#140
0%
#145
1%
#146
b101 0
1)
b1101 &
b1101 *
#150
0%
#155
b11 /
1%
#156
b110 0
0)
b10001101 &
b10001101 *
#160
0%
#165
1%
#166
b111 0
1)
b1100101 &
b1100101 *
#170
0%
#175
b100 /
1%
#176
b1000 0
0)
b10010 &
b10010 *
#180
0%
#185
1%
#186
b1001 0
1)
b1 &
b1 *
#190
0%
#195
b101 /
1%
#196
b1010 0
0)
b1101 &
b1101 *
#200
0%
#205
1%
#206
b1 1
1'
b1011 0
1)
b1110110 &
b1110110 *
#210
0%
#215
b1 .
b100100 #
b100100 -
b110 /
1%
#216
b1100 0
0)
b111101 &
b111101 *
b10 1
0'
#220
0%
#225
1%
#226
b11 1
b1101 0
1)
b11101101 &
b11101101 *
#230
0%
#235
b111 /
1%
#236
b1110 0
0)
b10001100 &
b10001100 *
b100 1
1'
#240
0%
#245
b10 .
b1001 #
b1001 -
1%
#246
b101 1
0'
b1111 0
1)
b11111001 &
b11111001 *
#250
0%
#255
b0 /
1%
#256
b10000 0
0)
b11000110 &
b11000110 *
b110 1
#260
0%
#265
1%
#266
b111 1
1'
b10001 0
1)
b11000101 &
b11000101 *
#270
0%
#275
b11 .
b1101 #
b1101 -
0!
b1 /
1%
#276
b10010 0
0)
b10101010 &
b10101010 *
b1000 1
0'
#280
0%
#285
1%
#286
b1001 1
b10011 0
1)
b11100101 &
b11100101 *
#290
0%
#295
1!
b10 /
1%
#296
b10100 0
0)
b1110111 &
b1110111 *
b1010 1
1'
#300
0%
#305
0!
b100 .
b1100101 #
b1100101 -
1%
#306
b1011 1
0'
b10101 0
1)
b10010 &
b10010 *
#310
0%
#315
1!
b11 /
1%
#316
b10110 0
0)
b10001111 &
b10001111 *
b1100 1
#320
0%
#325
1%
#326
b1101 1
1'
b10111 0
1)
b11110010 &
b11110010 *
#330
0%
#335
0!
b101 .
b1 #
b1 -
1%
#336
b11000 0
0)
b11001110 &
b11001110 *
b1110 1
0'
#340
0%
#345
1%
#346
b1111 1
b11001 0
1)
b11101000 &
b11101000 *
#350
0%
#355
1!
b100 /
1%
#356
b11010 0
0)
b11000101 &
b11000101 *
b10000 1
1'
#360
0%
#365
0!
b110 .
b1110110 #
b1110110 -
1%
#366
b10001 1
0'
b11011 0
1)
b1011100 &
b1011100 *
#370
0%
#375
1!
b101 /
1%
#376
b11100 0
0)
b10111101 &
b10111101 *
b10010 1
#380
0%
#385
1%
#386
b10011 1
1'
b11101 0
1)
b101101 &
b101101 *
#390
0%
#395
0!
b111 .
b11101101 #
b11101101 -
1%
#396
b11110 0
0)
b1100101 &
b1100101 *
b10100 1
0'
#400
0%
#405
1%
#406
b10101 1
#410
0%
#415
1%
#416
b10110 1
1'
#420
0%
#425
b0 .
b11111001 #
b11111001 -
1%
#426
b10111 1
0'
#430
0%
#435
1%
#436
b11000 1
#440
0%
#445
1%
#446
b11001 1
1'
b0 0
#450
0%
#455
b1 .
b11000101 #
b11000101 -
1%
#456
b1 0
1)
b1100011 &
b1100011 *
b11010 1
0'
#460
0%
#465
b110 /
1%
#466
b11011 1
b10 0
0)
b1010 &
b1010 *
#470
0%
#475
1%
#476
b11 0
1)
b10000000 &
b10000000 *
b11100 1
1'
#480
0%
#485
b111 /
b10 .
b11100101 #
b11100101 -
1%
#486
b11101 1
0'
b100 0
0)
b100000 &
b100000 *
#490
0%
#495
1%
#496
b101 0
1)
b10101010 &
b10101010 *
b11110 1
#500
0%
#505
b0 /
1%
#506
b110 0
0)
b10011101 &
b10011101 *
#510
0%
#515
1%
#516
b111 0
1)
b10010110 &
b10010110 *
#520
0%
#525
1!
b1 /
1%
#526
b1000 0
0)
b10011 &
b10011 *
#530
0%
#535
1%
#536
b1001 0
1)
b1101 &
b1101 *
#540
0%
#545
1%
#546
b1010 0
0)
b1010011 &
b1010011 *
b0 1
#550
0%
#555
1%
#556
b1 1
1'
b1011 0
1)
b1101011 &
b1101011 *
#560
0%
#565
0!
b11 .
b10010 #
b10010 -
1%
#566
b1100 0
0)
b11010101 &
b11010101 *
b10 1
0'
#570
0%
#575
1%
#576
b11 1
b1101 0
1)
b10 &
b10 *
#580
0%
#585
1!
b10 /
1%
#586
b1110 0
0)
b10101110 &
b10101110 *
b100 1
1'
#590
0%
#595
0!
b100 .
b11101000 #
b11101000 -
1%
#596
b101 1
0'
b1111 0
1)
b11101 &
b11101 *
#600
0%
#605
1!
b11 /
1%
#606
b10000 0
0)
b11001111 &
b11001111 *
b110 1
#610
0%
#615
1%
#616
b111 1
1'
b10001 0
1)
b100011 &
b100011 *
#620
0%
#625
0!
b101 .
b1011100 #
b1011100 -
1%
#626
b10010 0
0)
b1010 &
b1010 *
b1000 1
0'
#630
0%
#635
1%
#636
b1001 1
b10011 0
1)
b11001010 &
b11001010 *
#640
0%
#645
1!
b100 /
1%
#646
b10100 0
0)
b111100 &
b111100 *
b1010 1
1'
#650
0%
#655
0!
b110 .
b1100011 #
b1100011 -
1%
#656
b1011 1
0'
b10101 0
1)
b11110010 &
b11110010 *
#660
0%
#665
1!
b101 /
1%
#666
b10110 0
0)
b10001010 &
b10001010 *
b1100 1
#670
0%
#675
1%
#676
b1101 1
1'
b10111 0
1)
b1000001 &
b1000001 *
#680
0%
#685
0!
b111 .
b10000000 #
b10000000 -
1%
#686
b11000 0
0)
b11011000 &
b11011000 *
b1110 1
0'
#690
0%
#695
1%
#696
b1111 1
b11001 0
1)
b1111000 &
b1111000 *
#700
0%
#705
1!
b110 /
1%
#706
b11010 0
0)
b10001001 &
b10001001 *
b10000 1
1'
#710
0%
#715
0!
b0 .
b10101010 #
b10101010 -
1%
#716
b10001 1
0'
b11011 0
1)
b11101011 &
b11101011 *
#720
0%
#725
1!
b111 /
1%
#726
b11100 0
0)
b10110110 &
b10110110 *
b10010 1
#730
0%
#735
1%
#736
b10011 1
1'
b11101 0
1)
b11000110 &
b11000110 *
#740
0%
#745
0!
b1 .
b10010110 #
b10010110 -
1%
#746
b11110 0
0)
b10101110 &
b10101110 *
b10100 1
0'
#750
0%
#755
1%
#756
b10101 1
#760
0%
#765
1%
#766
b10110 1
1'
#770
0%
#775
b10 .
b10 #
b10 -
1%
#776
b10111 1
0'
#780
0%
#785
1%
#786
b11000 1
#790
0%
#795
1%
#796
b11001 1
1'
#800
0%
#805
b11 .
b11101 #
b11101 -
1%
#806
b11010 1
0'
#810
0%
#815
1%
#816
b11011 1
#820
0%
#825
1%
#826
b11100 1
1'
#830
0%
#835
b100 .
b11001010 #
b11001010 -
1%
#836
b11101 1
0'
#840
0%
#845
1%
#846
b11110 1
