example/fifo_latency/fifo.sv
module fifo #(
    parameter DEPTH = 2,
    DATA_WIDTH = 8
) (
    input clk,
    input rst_n,
    input w_en,
    input r_en,
    input [DATA_WIDTH-1:0] data_in,
    output reg [DATA_WIDTH-1:0] data_out,
    output full,
    output empty
);

    reg [$clog2(DEPTH)-1:0] w_ptr, r_ptr;
    reg [DATA_WIDTH-1:0] fifo[DEPTH];

    // Set Default values on reset.
    always @(posedge clk) begin
        if (!rst_n) begin
            w_ptr <= 0;
            r_ptr <= 0;
            data_out <= 0;
        end
    end

    // To write data to FIFO
    always @(posedge clk) begin
        if (w_en & !full) begin
            fifo[w_ptr] <= data_in;
            w_ptr <= w_ptr + 1;
        end
    end

    // To read data from FIFO
    always @(posedge clk) begin
        if (r_en & !empty) begin
            data_out <= fifo[r_ptr];
            r_ptr <= r_ptr + 1;
        end
    end

    assign full  = ((w_ptr + 1'b1) == r_ptr);
    assign empty = (w_ptr == r_ptr);
endmodule

example/scoreboard/fifo_tb.sv
module fifo_tb;
    parameter DATA_WIDTH = 8;

    reg clk, rst_n;
    reg w_en, r_en;
    reg  [DATA_WIDTH-1:0] data_in;
    wire [DATA_WIDTH-1:0] data_out;
    wire full, empty;

    fifo s_fifo (
        clk,
        rst_n,
        w_en,
        r_en,
        data_in,
        data_out,
        full,
        empty
    );

    always #5 clk = ~clk;

    initial begin
        clk = 1'b0;
        rst_n = 1'b0;
        w_en = 1'b0;
        data_in = 0;

        repeat (10) @(posedge clk);
        rst_n = 1'b1;

        // Ensure write starts after reset and gives some time
        #20;

        repeat (5) begin
            for (int i = 0; i < 30; i++) begin
                @(posedge clk);
                #1;
                data_in = $urandom;
                // Randomized write enable
                w_en = (i % 2 == 0) ? 1'b1 : 1'b0;

                if (w_en & !full) begin
                    $display("[%0t] wdata = %0d", $time, data_in);
                end
            end
            #50;
        end
    end

    initial begin
        clk   = 1'b0;
        rst_n = 1'b0;
        r_en  = 1'b0;

        repeat (20) @(posedge clk);
        rst_n = 1'b1;

        // Wait for some data to be written
        // Wait until at least one write has happened
        @(posedge clk);
        wait (s_fifo.w_ptr != 0);
        #1; // Delay to avoid sampling issues if r_en goes high same cycle? No, just wait a bit.

        repeat (5) begin
            for (int i = 0; i < 30; i++) begin
                @(posedge clk);
                #1;
                // Randomized read enable
                r_en = (i % 3 == 0) ? 1'b1 : 1'b0;
                if (r_en & !empty) begin
                    $display("[%0t] rdata = %0d", $time, data_out);
                end
            end
            #50;
        end

        $finish;
    end

    initial begin
        $dumpfile("fifo_tb.vcd");
        $dumpvars;
    end
endmodule

example/scoreboard/fifo_tb.vcd
$date
	Sun Jan 25 20:33:26 2026
$end
$version
	Icarus Verilog
$end
$timescale
	1s
$end
$scope module fifo_tb $end
$var wire 1 ! full $end
$var wire 1 " empty $end
$var wire 8 # data_out [7:0] $end
$var parameter 32 $ DATA_WIDTH $end
$var reg 1 % clk $end
$var reg 8 & data_in [7:0] $end
$var reg 1 ' r_en $end
$var reg 1 ( rst_n $end
$var reg 1 ) w_en $end
$scope module s_fifo $end
$var wire 1 % clk $end
$var wire 8 * data_in [7:0] $end
$var wire 1 " empty $end
$var wire 1 ! full $end
$var wire 1 ' r_en $end
$var wire 1 ( rst_n $end
$var wire 1 ) w_en $end
$var parameter 32 + DATA_WIDTH $end
$var parameter 32 , DEPTH $end
$var reg 8 - data_out [7:0] $end
$var reg 1 . r_ptr $end
$var reg 1 / w_ptr $end
$upscope $end
$scope begin $ivl_for_loop0 $end
$var integer 32 0 i [31:0] $end
$upscope $end
$scope begin $ivl_for_loop1 $end
$var integer 32 1 i [31:0] $end
$upscope $end
$upscope $end
$enddefinitions $end
$comment Show the parameter values. $end
$dumpall
b10 ,
b1000 +
b1000 $
$end
#0
$dumpvars
b0 1
b0 0
x/
x.
bx -
b0 *
0)
0(
0'
b0 &
0%
bx #
x"
x!
$end
#5
0!
1"
b0 #
b0 -
0.
0/
1%
#10
0%
#15
1%
#20
0%
#25
1%
#30
0%
#35
1%
#40
0%
#45
1%
#50
0%
#55
1%
#60
0%
#65
1%
#70
0%
#75
1%
#80
0%
#85
1%
#90
0%
#95
1(
1%
#100
0%
#105
1%
#110
0%
#115
1%
#116
b1 0
1)
b100100 &
b100100 *
#120
0%
#125
1!
0"
1/
1%
#126
b10 0
0)
b10000001 &
b10000001 *
#130
0%
#135
1%
#136
b11 0
1)
b1001 &
b1001 *
#140
0%
#145
1%
#146
b100 0
0)
b1100011 &
b1100011 *
#150
0%
#155
1%
#156
b101 0
1)
b1101 &
b1101 *
#160
0%
#165
1%
#166
b110 0
0)
b10001101 &
b10001101 *
#170
0%
#175
1%
#176
b111 0
1)
b1100101 &
b1100101 *
#180
0%
#185
1%
#186
b1000 0
0)
b10010 &
b10010 *
#190
0%
#195
1%
#196
b1001 0
1)
b1 &
b1 *
#200
0%
#205
1%
#206
b1010 0
0)
b1101 &
b1101 *
#210
0%
#215
1%
#216
b1011 0
1)
b1110110 &
b1110110 *
b1 1
1'
#220
0%
#225
1"
0!
1.
b100100 #
b100100 -
1%
#226
b10 1
0'
b1100 0
0)
b111101 &
b111101 *
#230
0%
#235
1%
#236
b1101 0
1)
b11101101 &
b11101101 *
b11 1
#240
0%
#245
1!
0"
0/
1%
#246
b100 1
1'
b1110 0
0)
b10001100 &
b10001100 *
#250
0%
#255
1"
0!
0.
b11101101 #
b11101101 -
1%
#256
b1111 0
1)
b11111001 &
b11111001 *
b101 1
0'
#260
0%
#265
1!
0"
1/
1%
#266
b110 1
b10000 0
0)
b11000110 &
b11000110 *
#270
0%
#275
1%
#276
b10001 0
1)
b11000101 &
b11000101 *
b111 1
1'
#280
0%
#285
1"
0!
1.
b11111001 #
b11111001 -
1%
#286
b1000 1
0'
b10010 0
0)
b10101010 &
b10101010 *
#290
0%
#295
1%
#296
b10011 0
1)
b11100101 &
b11100101 *
b1001 1
#300
0%
#305
1!
0"
0/
1%
#306
b1010 1
1'
b10100 0
0)
b1110111 &
b1110111 *
#310
0%
#315
1"
0!
0.
b11100101 #
b11100101 -
1%
#316
b10101 0
1)
b10010 &
b10010 *
b1011 1
0'
#320
0%
#325
1!
0"
1/
1%
#326
b1100 1
b10110 0
0)
b10001111 &
b10001111 *
#330
0%
#335
1%
#336
b10111 0
1)
b11110010 &
b11110010 *
b1101 1
1'
#340
0%
#345
1"
0!
1.
b10010 #
b10010 -
1%
#346
b1110 1
0'
b11000 0
0)
b11001110 &
b11001110 *
#350
0%
#355
1%
#356
b11001 0
1)
b11101000 &
b11101000 *
b1111 1
#360
0%
#365
1!
0"
0/
1%
#366
b10000 1
1'
b11010 0
0)
b11000101 &
b11000101 *
#370
0%
#375
1"
0!
0.
b11101000 #
b11101000 -
1%
#376
b11011 0
1)
b1011100 &
b1011100 *
b10001 1
0'
#380
0%
#385
1!
0"
1/
1%
#386
b10010 1
b11100 0
0)
b10111101 &
b10111101 *
#390
0%
#395
1%
#396
b11101 0
1)
b101101 &
b101101 *
b10011 1
1'
#400
0%
#405
1"
0!
1.
b1011100 #
b1011100 -
1%
#406
b10100 1
0'
b11110 0
0)
b1100101 &
b1100101 *
#410
0%
#415
1%
#416
b10101 1
#420
0%
#425
1%
#426
b10110 1
1'
#430
0%
#435
1%
#436
b10111 1
0'
#440
0%
#445
1%
#446
b11000 1
#450
0%
#455
1%
#456
b11001 1
1'
b0 0
#460
0%
#465
1%
#466
b1 0
1)
b1100011 &
b1100011 *
b11010 1
0'
#470
0%
#475
1!
0"
0/
1%
#476
b11011 1
b10 0
0)
b1010 &
b1010 *
#480
0%
#485
1%
#486
b11 0
1)
b10000000 &
b10000000 *
b11100 1
1'
#490
0%
#495
1"
0!
0.
b1100011 #
b1100011 -
1%
#496
b11101 1
0'
b100 0
0)
b100000 &
b100000 *
#500
0%
#505
1%
#506
b101 0
1)
b10101010 &
b10101010 *
b11110 1
#510
0%
#515
1!
0"
1/
1%
#516
b110 0
0)
b10011101 &
b10011101 *
#520
0%
#525
1%
#526
b111 0
1)
b10010110 &
b10010110 *
#530
0%
#535
1%
#536
b1000 0
0)
b10011 &
b10011 *
#540
0%
#545
1%
#546
b1001 0
1)
b1101 &
b1101 *
#550
0%
#555
1%
#556
b1010 0
0)
b1010011 &
b1010011 *
b0 1
#560
0%
#565
1%
#566
b1 1
1'
b1011 0
1)
b1101011 &
b1101011 *
#570
0%
#575
1"
0!
1.
b10101010 #
b10101010 -
1%
#576
b1100 0
0)
b11010101 &
b11010101 *
b10 1
0'
#580
0%
#585
1%
#586
b11 1
b1101 0
1)
b10 &
b10 *
#590
0%
#595
1!
0"
0/
1%
#596
b1110 0
0)
b10101110 &
b10101110 *
b100 1
1'
#600
0%
#605
1"
0!
0.
b10 #
b10 -
1%
#606
b101 1
0'
b1111 0
1)
b11101 &
b11101 *
#610
0%
#615
1!
0"
1/
1%
#616
b10000 0
0)
b11001111 &
b11001111 *
b110 1
#620
0%
#625
1%
#626
b111 1
1'
b10001 0
1)
b100011 &
b100011 *
#630
0%
#635
1"
0!
1.
b11101 #
b11101 -
1%
#636
b10010 0
0)
b1010 &
b1010 *
b1000 1
0'
#640
0%
#645
1%
#646
b1001 1
b10011 0
1)
b11001010 &
b11001010 *
#650
0%
#655
1!
0"
0/
1%
#656
b10100 0
0)
b111100 &
b111100 *
b1010 1
1'
#660
0%
#665
1"
0!
0.
b11001010 #
b11001010 -
1%
#666
b1011 1
0'
b10101 0
1)
b11110010 &
b11110010 *
#670
0%
#675
1!
0"
1/
1%
#676
b10110 0
0)
b10001010 &
b10001010 *
b1100 1
#680
0%
#685
1%
#686
b1101 1
1'
b10111 0
1)
b1000001 &
b1000001 *
#690
0%
#695
1"
0!
1.
b11110010 #
b11110010 -
1%
#696
b11000 0
0)
b11011000 &
b11011000 *
b1110 1
0'
#700
0%
#705
1%
#706
b1111 1
b11001 0
1)
b1111000 &
b1111000 *
#710
0%
#715
1!
0"
0/
1%
#716
b11010 0
0)
b10001001 &
b10001001 *
b10000 1
1'
#720
0%
#725
1"
0!
0.
b1111000 #
b1111000 -
1%
#726
b10001 1
0'
b11011 0
1)
b11101011 &
b11101011 *
#730
0%
#735
1!
0"
1/
1%
#736
b11100 0
0)
b10110110 &
b10110110 *
b10010 1
#740
0%
#745
1%
#746
b10011 1
1'
b11101 0
1)
b11000110 &
b11000110 *
#750
0%
#755
1"
0!
1.
b11101011 #
b11101011 -
1%
#756
b11110 0
0)
b10101110 &
b10101110 *
b10100 1
0'
#760
0%
#765
1%
#766
b10101 1
#770
0%
#775
1%
#776
b10110 1
1'
#780
0%
#785
1%
#786
b10111 1
0'
#790
0%
#795
1%
#796
b11000 1
#800
0%
#805
1%
#806
b11001 1
1'
b0 0
#810
0%
#815
1%
#816
b1 0
1)
b10111100 &
b10111100 *
b11010 1
0'
#820
0%
#825
1!
0"
0/
1%
#826
b11011 1
b10 0
0)
b101010 &
b101010 *
#830
0%
#835
1%
#836
b11 0
1)
b1011 &
b1011 *
b11100 1
1'
#840
0%
#845
1"
0!
0.
b10111100 #
b10111100 -
1%
#846
b11101 1
0'
b100 0
0)
b1110001 &
b1110001 *
#850
0%
#855
1%
#856
b101 0
1)
b10000101 &
b10000101 *
b11110 1
#860
0%
#865
1!
0"
1/
1%
#866
b110 0
0)
b1001111 &
b1001111 *
#870
0%
#875
1%
#876
b111 0
1)
b111011 &
b111011 *
#880
0%
#885
1%
#886
b1000 0
0)
b111010 &
b111010 *
#890
0%
#895
1%
#896
b1001 0
1)
b1111110 &
b1111110 *
#900
0%
#905
1%
#906
b1010 0
0)
b10101 &
b10101 *
b0 1
#910
0%
#915
1%
#916
b1 1
1'
b1011 0
1)
b11110001 &
b11110001 *
#920
0%
#925
1"
0!
1.
b10000101 #
b10000101 -
1%
#926
b1100 0
0)
b11011001 &
b11011001 *
b10 1
0'
#930
0%
#935
1%
#936
b11 1
b1101 0
1)
b1100010 &
b1100010 *
#940
0%
#945
1!
0"
0/
1%
#946
b1110 0
0)
b1001100 &
b1001100 *
b100 1
1'
#950
0%
#955
1"
0!
0.
b1100010 #
b1100010 -
1%
#956
b101 1
0'
b1111 0
1)
b10011111 &
b10011111 *
#960
0%
#965
1!
0"
1/
1%
#966
b10000 0
0)
b10001111 &
b10001111 *
b110 1
#970
0%
#975
1%
#976
b111 1
1'
b10001 0
1)
b11111000 &
b11111000 *
#980
0%
#985
1"
0!
1.
b10011111 #
b10011111 -
1%
#986
b10010 0
0)
b10110111 &
b10110111 *
b1000 1
0'
#990
0%
#995
1%
#996
b1001 1
b10011 0
1)
b10011111 &
b10011111 *
#1000
0%
#1005
1!
0"
0/
1%
#1006
b10100 0
0)
b1011100 &
b1011100 *
b1010 1
1'
#1010
0%
#1015
1"
0!
0.
1%
#1016
b1011 1
0'
b10101 0
1)
b1011011 &
b1011011 *
#1020
0%
#1025
1!
0"
1/
1%
#1026
b10110 0
0)
b10001001 &
b10001001 *
b1100 1
#1030
0%
#1035
1%
#1036
b1101 1
1'
b10111 0
1)
b1001001 &
b1001001 *
#1040
0%
#1045
1"
0!
1.
b1011011 #
b1011011 -
1%
#1046
b11000 0
0)
b11010000 &
b11010000 *
b1110 1
0'
#1050
0%
#1055
1%
#1056
b1111 1
b11001 0
1)
b11010111 &
b11010111 *
#1060
0%
#1065
1!
0"
0/
1%
#1066
b11010 0
0)
b1010001 &
b1010001 *
b10000 1
1'
#1070
0%
#1075
1"
0!
0.
b11010111 #
b11010111 -
1%
#1076
b10001 1
0'
b11011 0
1)
b10010110 &
b10010110 *
#1080
0%
#1085
1!
0"
1/
1%
#1086
b11100 0
0)
b1100 &
b1100 *
b10010 1
#1090
0%
#1095
1%
#1096
b10011 1
1'
b11101 0
1)
b11000010 &
b11000010 *
#1100
0%
#1105
1"
0!
1.
b10010110 #
b10010110 -
1%
#1106
b11110 0
0)
b11001000 &
b11001000 *
b10100 1
0'
#1110
0%
#1115
1%
#1116
b10101 1
#1120
0%
#1125
1%
#1126
b10110 1
1'
#1130
0%
#1135
1%
#1136
b10111 1
0'
#1140
0%
#1145
1%
#1146
b11000 1
#1150
0%
#1155
1%
#1156
b11001 1
1'
b0 0
#1160
0%
#1165
1%
#1166
b1 0
1)
b1110111 &
b1110111 *
b11010 1
0'
#1170
0%
#1175
1!
0"
0/
1%
#1176
b11011 1
b10 0
0)
b111101 &
b111101 *
#1180
0%
#1185
1%
#1186
b11 0
1)
b10010 &
b10010 *
b11100 1
1'
#1190
0%
#1195
1"
0!
0.
b1110111 #
b1110111 -
1%
#1196
b11101 1
0'
b100 0
0)
b1111110 &
b1111110 *
#1200
0%
#1205
1%
#1206
b101 0
1)
b1101101 &
b1101101 *
b11110 1
#1210
0%
#1215
1!
0"
1/
1%
#1216
b110 0
0)
b111001 &
b111001 *
#1220
0%
#1225
1%
#1226
b111 0
1)
b11111 &
b11111 *
#1230
0%
#1235
1%
#1236
b1000 0
0)
b11010011 &
b11010011 *
#1240
0%
#1245
1%
#1246
b1001 0
1)
b10000101 &
b10000101 *
#1250
0%
#1255
1%
#1256
b1010 0
0)
b1111000 &
b1111000 *
b0 1
#1260
0%
#1265
1%
#1266
b1 1
1'
b1011 0
1)
b1011011 &
b1011011 *
#1270
0%
#1275
1"
0!
1.
b1101101 #
b1101101 -
1%
#1276
b1100 0
0)
b1001001 &
b1001001 *
b10 1
0'
#1280
0%
#1285
1%
#1286
b11 1
b1101 0
1)
b111111 &
b111111 *
#1290
0%
#1295
1!
0"
0/
1%
#1296
b1110 0
0)
b101010 &
b101010 *
b100 1
1'
#1300
0%
#1305
1"
0!
0.
b111111 #
b111111 -
1%
#1306
b101 1
0'
b1111 0
1)
b1011000 &
b1011000 *
#1310
0%
#1315
1!
0"
1/
1%
#1316
b10000 0
0)
b10000110 &
b10000110 *
b110 1
#1320
0%
#1325
1%
#1326
b111 1
1'
b10001 0
1)
b10001110 &
b10001110 *
#1330
0%
#1335
1"
0!
1.
b1011000 #
b1011000 -
1%
#1336
b10010 0
0)
b10011100 &
b10011100 *
b1000 1
0'
#1340
0%
#1345
1%
#1346
b1001 1
b10011 0
1)
b11111010 &
b11111010 *
#1350
0%
#1355
1!
0"
0/
1%
#1356
b10100 0
0)
b100110 &
b100110 *
b1010 1
1'
#1360
0%
#1365
1"
0!
0.
b11111010 #
b11111010 -
1%
#1366
b1011 1
0'
b10101 0
1)
b1110011 &
b1110011 *
#1370
0%
#1375
1!
0"
1/
1%
#1376
b10110 0
0)
b10100011 &
b10100011 *
b1100 1
#1380
0%
#1385
1%
#1386
b1101 1
1'
b10111 0
1)
b101111 &
b101111 *
#1390
0%
#1395
1"
0!
1.
b1110011 #
b1110011 -
1%
#1396
b11000 0
0)
b10110011 &
b10110011 *
b1110 1
0'
#1400
0%
#1405
1%
#1406
b1111 1
b11001 0
1)
b1011111 &
b1011111 *
#1410
0%
#1415
1!
0"
0/
1%
#1416
b11010 0
0)
b1000100 &
b1000100 *
b10000 1
1'
#1420
0%
#1425
1"
0!
0.
b1011111 #
b1011111 -
1%
#1426
b10001 1
0'
b11011 0
1)
b11110111 &
b11110111 *
#1430
0%
#1435
1!
0"
1/
1%
#1436
b11100 0
0)
b11001011 &
b11001011 *
b10010 1
#1440
0%
#1445
1%
#1446
b10011 1
1'
b11101 0
1)
b11100110 &
b11100110 *
#1450
0%
#1455
1"
0!
1.
b11110111 #
b11110111 -
1%
#1456
b11110 0
0)
b1011010 &
b1011010 *
b10100 1
0'
#1460
0%
#1465
1%
#1466
b10101 1
#1470
0%
#1475
1%
#1476
b10110 1
1'
#1480
0%
#1485
1%
#1486
b10111 1
0'
#1490
0%
#1495
1%
#1496
b11000 1
#1500
0%
#1505
1%
#1506
b11001 1
1'
b0 0
#1510
0%
#1515
1%
#1516
b1 0
1)
b101001 &
b101001 *
b11010 1
0'
#1520
0%
#1525
1!
0"
0/
1%
#1526
b11011 1
b10 0
0)
b11101101 &
b11101101 *
#1530
0%
#1535
1%
#1536
b11 0
1)
b11011010 &
b11011010 *
b11100 1
1'
#1540
0%
#1545
1"
0!
0.
b101001 #
b101001 -
1%
#1546
b11101 1
0'
b100 0
0)
b1100101 &
b1100101 *
#1550
0%
#1555
1%
#1556
b101 0
1)
b10110101 &
b10110101 *
b11110 1
#1560
0%
#1565
1!
0"
1/
1%
#1566
b110 0
0)
b11011111 &
b11011111 *
#1570
0%
#1575
1%
#1576
b111 0
1)
b1111001 &
b1111001 *
#1580
0%
#1585
1%
#1586
b1000 0
0)
b1000100 &
b1000100 *
#1590
0%
#1595
1%
#1596
b1001 0
1)
b11010000 &
b11010000 *
#1600
0%
#1605
1%
#1606
b1010 0
0)
b101010 &
b101010 *
b0 1
#1610
0%
#1615
1%
#1616
b1 1
1'
b1011 0
1)
b10101011 &
b10101011 *
#1620
0%
#1625
1"
0!
1.
b10110101 #
b10110101 -
1%
#1626
b1100 0
0)
b1110 &
b1110 *
b10 1
0'
#1630
0%
#1635
1%
#1636
b11 1
b1101 0
1)
b11011100 &
b11011100 *
#1640
0%
#1645
1!
0"
0/
1%
#1646
b1110 0
0)
b10011010 &
b10011010 *
b100 1
1'
#1650
0%
#1655
1"
0!
0.
b11011100 #
b11011100 -
1%
#1656
b101 1
0'
b1111 0
1)
b11111101 &
b11111101 *
#1660
0%
#1665
1!
0"
1/
1%
#1666
b10000 0
0)
b11000011 &
b11000011 *
b110 1
#1670
0%
#1675
1%
#1676
b111 1
1'
b10001 0
1)
b1010110 &
b1010110 *
#1680
0%
#1685
1"
0!
1.
b11111101 #
b11111101 -
1%
#1686
b10010 0
0)
b1001110 &
b1001110 *
b1000 1
0'
#1690
0%
#1695
1%
#1696
b1001 1
b10011 0
1)
b1100111 &
b1100111 *
#1700
0%
#1705
1!
0"
0/
1%
#1706
b10100 0
0)
b1010 &
b1010 *
b1010 1
1'
#1710
0%
#1715
1"
0!
0.
b1100111 #
b1100111 -
1%
#1716
b1011 1
0'
b10101 0
1)
b10110110 &
b10110110 *
#1720
0%
#1725
1!
0"
1/
1%
#1726
b10110 0
0)
b111000 &
b111000 *
b1100 1
#1730
0%
#1735
1%
#1736
b1101 1
1'
b10111 0
1)
b1111001 &
b1111001 *
#1740
0%
#1745
1"
0!
1.
b10110110 #
b10110110 -
1%
#1746
b11000 0
0)
b10111000 &
b10111000 *
b1110 1
0'
#1750
0%
#1755
1%
#1756
b1111 1
b11001 0
1)
b10010100 &
b10010100 *
#1760
0%
#1765
1!
0"
0/
1%
#1766
b11010 0
0)
b10010011 &
b10010011 *
b10000 1
1'
#1770
0%
#1775
1"
0!
0.
b10010100 #
b10010100 -
1%
#1776
b10001 1
0'
b11011 0
1)
b100 &
b100 *
#1780
0%
#1785
1!
0"
1/
1%
#1786
b11100 0
0)
b1011001 &
b1011001 *
b10010 1
#1790
0%
#1795
1%
#1796
b10011 1
1'
b11101 0
1)
b11011011 &
b11011011 *
#1800
0%
#1805
1"
0!
1.
b100 #
b100 -
1%
#1806
b11110 0
0)
b1001101 &
b1001101 *
b10100 1
0'
#1810
0%
#1815
1%
#1816
b10101 1
#1820
0%
#1825
1%
#1826
b10110 1
1'
#1830
0%
#1835
1%
#1836
b10111 1
0'
#1840
0%
#1845
1%
#1846
b11000 1
#1850
0%
#1855
1%
#1856
b11001 1
1'
#1860
0%
#1865
1%
#1866
b11010 1
0'
#1870
0%
#1875
1%
#1876
b11011 1
#1880
0%
#1885
1%
#1886
b11100 1
1'
#1890
0%
#1895
1%
#1896
b11101 1
0'
#1900
0%
#1905
1%
#1906
b11110 1
